{
  "id": "yigidin-harman-oldugu-deste.tr",
  "name": "Yiğidin harman olduğu deste",
  "language": "tr",
  "difficulty": "hard",
  "words": [
    {
      "term": "Kart hamili",
      "hint": "Banka veya kredi ödeme aracının üzerinde adı yazan yasal sahibi.",
      "difficulty": 3
    },
    {
      "term": "Kabin",
      "hint": "Mağazalarda kıyafet denenen veya uçaklarda yolcuların bulunduğu kapalı alan.",
      "difficulty": 1
    },
    {
      "term": "Zabıt",
      "hint": "Meclis veya mahkeme gibi yerlerde söylenenlerin aynen yazıldığı tutanak.",
      "difficulty": 2
    },
    {
      "term": "Zehir taciri",
      "hint": "Yasa dışı uyuşturucu maddelerin ticaretini yapan kişi.",
      "difficulty": 2
    },
    {
      "term": "Platonik",
      "hint": "Gerçekleşmesi beklenmeyen, tek taraflı yaşanan duygusal yakınlık.",
      "difficulty": 1
    },
    {
      "term": "Ruhospu",
      "hint": "Ruhsar dizisinde Mashar'ın ölü eşine kızdığında söylediği hitap.",
      "difficulty": 3
    },
    {
      "term": "Gelin arabası",
      "hint": "Evlilik töreninde çiftlerin bindiği süslü taşıt.",
      "difficulty": 1
    },
    {
      "term": "Domino",
      "hint": "Üzerinde sayıları temsil eden noktalar olan taşlarla oynanan bir oyun.",
      "difficulty": 1
    },
    {
      "term": "Ben bu yaz neredeydim?",
      "hint": "Hababam Sınıfı filminde Badi Ekrem karakterinin bir repliği.",
      "difficulty": 2
    },
    {
      "term": "Kuşkonmaz",
      "hint": "Uç kısımları yenen, zambakgiller ailesinden uzun ve ince bir sebze.",
      "difficulty": 2
    },
    {
      "term": "İt dalaşı",
      "hint": "Savaş uçaklarının birbirini taciz etmek için yaptığı manevralar.",
      "difficulty": 2
    },
    {
      "term": "Botanik",
      "hint": "Bitki dünyasını bilimsel olarak inceleyen biyoloji dalı.",
      "difficulty": 1
    },
    {
      "term": "Ören Bayan",
      "hint": "Televizyon reklamlarındaki kadın figürüyle tanınan nakış ipliği markası.",
      "difficulty": 2
    },
    {
      "term": "Kurpiyer",
      "hint": "Oyun salonlarında masadaki bahisleri ve kağıtları yöneten görevli.",
      "difficulty": 2
    },
    {
      "term": "İroni",
      "hint": "Bir durumun, beklenen veya söylenen şeyin tam tersi şekilde gerçekleşmesi.",
      "difficulty": 2
    },
    {
      "term": "livemealone",
      "hint": "GTA Vice City oyununda polisten kurtulmayı sağlayan meşhur hile kodu.",
      "difficulty": 3
    },
    {
      "term": "Şahane Pazar",
      "hint": "90'lı yıllarda Uygur kardeşlerin sunduğu efsanevi eğlence programı.",
      "difficulty": 2
    },
    {
      "term": "Adam asmaca",
      "hint": "Doğru harf bulunamazsa bir figürün sehpasının tamamlandığı kelime oyunu.",
      "difficulty": 1
    },
    {
      "term": "Bıyık",
      "hint": "Erkeklerde üst dudak bölgesinde uzatılan kıllar.",
      "difficulty": 1
    },
    {
      "term": "Korsan taksi",
      "hint": "Yasal izni olmadan taşımacılık yapan binek araç.",
      "difficulty": 1
    },
    {
      "term": "Sukulent",
      "hint": "Gövdesinde su biriktiren, etli yapraklı süs bitkisi.",
      "difficulty": 1
    },
    {
      "term": "Kumarhane",
      "hint": "Şans oyunlarının büyük çapta ve profesyonelce oynatıldığı mekan.",
      "difficulty": 1
    },
    {
      "term": "Telsiz",
      "hint": "Kablolu bağlantı olmadan ses dalgalarıyla iletişim kuran cihaz.",
      "difficulty": 1
    },
    {
      "term": "Baklava",
      "hint": "İnce yufkaların arasına fıstık veya ceviz konularak yapılan şerbetli tatlı.",
      "difficulty": 1
    },
    {
      "term": "Çaydanlık",
      "hint": "Demleme işleminin yapıldığı üst üste oturtulan mutfak gereci.",
      "difficulty": 1
    },
    {
      "term": "Nostalji",
      "hint": "Geçmişe duyulan özlem ve eski günleri yad etme durumu.",
      "difficulty": 2
    },
    {
      "term": "Kırmızı ışık",
      "hint": "Trafikte araçların durması gerektiğini bildiren uyarı.",
      "difficulty": 1
    },
    {
      "term": "Sosyal medya",
      "hint": "İnternet üzerinde kişilerin paylaşım yaptığı ve etkileşime girdiği platformlar.",
      "difficulty": 1
    },
    {
      "term": "Mangal",
      "hint": "Açık havada kömür ateşinde et pişirmeye yarayan düzenek.",
      "difficulty": 1
    },
    {
      "term": "Tavla",
      "hint": "Pullar ve zarlarla ahşap bir zemin üzerinde oynanan geleneksel oyun.",
      "difficulty": 1
    },
    {
      "term": "Şezlong",
      "hint": "Plajlarda üzerine uzanılan uzun ve ayarlanabilir sandalye.",
      "difficulty": 1
    },
    {
      "term": "Kolonya",
      "hint": "Hoş kokulu, ferahlatıcı ve içinde alkol bulunan sıvı.",
      "difficulty": 1
    },
    {
      "term": "Nazar boncuğu",
      "hint": "Kötü enerjiden koruduğuna inanılan mavi renkli cam nesne.",
      "difficulty": 1
    },
    {
      "term": "Bayram harçlığı",
      "hint": "Dini özel günlerde büyüklerin küçüklere verdiği para.",
      "difficulty": 2
    },
    {
      "term": "Vesikalık",
      "hint": "Resmi belgeler için çektirilen, sadece baş ve omuz bölgesini gösteren fotoğraf.",
      "difficulty": 2
    },
    {
      "term": "Uzaktan kumanda",
      "hint": "Televizyon veya cihazları yerinden kalkmadan yönetmeye yarayan alet.",
      "difficulty": 1
    },
    {
      "term": "Görüntülü arama",
      "hint": "Telefonla konuşurken karşıdaki kişiyi ekran üzerinden izleme işlemi.",
      "difficulty": 2
    },
    {
      "term": "Eskici",
      "hint": "Kullanılmayan eşyaları satın alan veya sokaklarda toplayan kimse.",
      "difficulty": 2
    },
    {
      "term": "Amorti",
      "hint": "Piyango biletine ödenen paranın ikramiye olarak geri alınması.",
      "difficulty": 2
    },
    {
      "term": "Tost",
      "hint": "İki ekmek arasına malzeme konularak makinede ısıtılan pratik yiyecek.",
      "difficulty": 1
    }
  ]
}